{"frames": {

"light_5_00000.png":
{
	"frame": {"x":537,"y":265,"w":243,"h":360},
	"rotated": true,
	"trimmed": true,
	"spriteSourceSize": {"x":68,"y":0,"w":243,"h":360},
	"sourceSize": {"w":314,"h":391}
},
"light_5_00001.png":
{
	"frame": {"x":536,"y":510,"w":243,"h":360},
	"rotated": true,
	"trimmed": true,
	"spriteSourceSize": {"x":68,"y":0,"w":243,"h":360},
	"sourceSize": {"w":314,"h":391}
},
"light_5_00002.png":
{
	"frame": {"x":898,"y":510,"w":243,"h":360},
	"rotated": true,
	"trimmed": true,
	"spriteSourceSize": {"x":68,"y":0,"w":243,"h":360},
	"sourceSize": {"w":314,"h":391}
},
"light_5_00003.png":
{
	"frame": {"x":899,"y":264,"w":244,"h":359},
	"rotated": true,
	"trimmed": true,
	"spriteSourceSize": {"x":67,"y":0,"w":244,"h":359},
	"sourceSize": {"w":314,"h":391}
},
"light_5_00004.png":
{
	"frame": {"x":534,"y":1015,"w":244,"h":359},
	"rotated": true,
	"trimmed": true,
	"spriteSourceSize": {"x":67,"y":0,"w":244,"h":359},
	"sourceSize": {"w":314,"h":391}
},
"light_5_00005.png":
{
	"frame": {"x":1156,"y":1271,"w":244,"h":359},
	"rotated": true,
	"trimmed": true,
	"spriteSourceSize": {"x":67,"y":0,"w":244,"h":359},
	"sourceSize": {"w":314,"h":391}
},
"light_5_00006.png":
{
	"frame": {"x":1600,"y":766,"w":245,"h":359},
	"rotated": true,
	"trimmed": true,
	"spriteSourceSize": {"x":66,"y":0,"w":245,"h":359},
	"sourceSize": {"w":314,"h":391}
},
"light_5_00007.png":
{
	"frame": {"x":1517,"y":1268,"w":246,"h":358},
	"rotated": true,
	"trimmed": true,
	"spriteSourceSize": {"x":65,"y":0,"w":246,"h":358},
	"sourceSize": {"w":314,"h":391}
},
"light_5_00008.png":
{
	"frame": {"x":530,"y":1261,"w":246,"h":358},
	"rotated": true,
	"trimmed": true,
	"spriteSourceSize": {"x":65,"y":0,"w":246,"h":358},
	"sourceSize": {"w":314,"h":391}
},
"light_5_00009.png":
{
	"frame": {"x":1260,"y":260,"w":248,"h":357},
	"rotated": true,
	"trimmed": true,
	"spriteSourceSize": {"x":63,"y":0,"w":248,"h":357},
	"sourceSize": {"w":314,"h":391}
},
"light_5_00010.png":
{
	"frame": {"x":1260,"y":510,"w":249,"h":356},
	"rotated": true,
	"trimmed": true,
	"spriteSourceSize": {"x":62,"y":0,"w":249,"h":356},
	"sourceSize": {"w":314,"h":391}
},
"light_5_00011.png":
{
	"frame": {"x":1242,"y":761,"w":250,"h":356},
	"rotated": true,
	"trimmed": true,
	"spriteSourceSize": {"x":61,"y":0,"w":250,"h":356},
	"sourceSize": {"w":314,"h":391}
},
"light_5_00012.png":
{
	"frame": {"x":1618,"y":513,"w":251,"h":355},
	"rotated": true,
	"trimmed": true,
	"spriteSourceSize": {"x":60,"y":0,"w":251,"h":355},
	"sourceSize": {"w":314,"h":391}
},
"light_5_00013.png":
{
	"frame": {"x":1510,"y":1013,"w":253,"h":354},
	"rotated": true,
	"trimmed": true,
	"spriteSourceSize": {"x":58,"y":0,"w":253,"h":354},
	"sourceSize": {"w":314,"h":391}
},
"light_5_00014.png":
{
	"frame": {"x":1593,"y":1,"w":254,"h":354},
	"rotated": true,
	"trimmed": true,
	"spriteSourceSize": {"x":57,"y":0,"w":254,"h":354},
	"sourceSize": {"w":314,"h":391}
},
"light_5_00015.png":
{
	"frame": {"x":1619,"y":257,"w":254,"h":354},
	"rotated": true,
	"trimmed": true,
	"spriteSourceSize": {"x":56,"y":0,"w":254,"h":354},
	"sourceSize": {"w":314,"h":391}
},
"light_5_00016.png":
{
	"frame": {"x":887,"y":755,"w":255,"h":353},
	"rotated": true,
	"trimmed": true,
	"spriteSourceSize": {"x":55,"y":0,"w":255,"h":353},
	"sourceSize": {"w":314,"h":391}
},
"light_5_00017.png":
{
	"frame": {"x":1156,"y":1013,"w":256,"h":352},
	"rotated": true,
	"trimmed": true,
	"spriteSourceSize": {"x":54,"y":0,"w":256,"h":352},
	"sourceSize": {"w":314,"h":391}
},
"light_5_00018.png":
{
	"frame": {"x":1239,"y":1,"w":257,"h":352},
	"rotated": true,
	"trimmed": true,
	"spriteSourceSize": {"x":53,"y":0,"w":257,"h":352},
	"sourceSize": {"w":314,"h":391}
},
"light_5_00019.png":
{
	"frame": {"x":534,"y":755,"w":258,"h":351},
	"rotated": true,
	"trimmed": true,
	"spriteSourceSize": {"x":52,"y":0,"w":258,"h":351},
	"sourceSize": {"w":314,"h":391}
},
"light_5_00020.png":
{
	"frame": {"x":895,"y":1012,"w":259,"h":350},
	"rotated": false,
	"trimmed": true,
	"spriteSourceSize": {"x":51,"y":0,"w":259,"h":350},
	"sourceSize": {"w":314,"h":391}
},
"light_5_00021.png":
{
	"frame": {"x":888,"y":1,"w":261,"h":349},
	"rotated": true,
	"trimmed": true,
	"spriteSourceSize": {"x":49,"y":0,"w":261,"h":349},
	"sourceSize": {"w":314,"h":391}
},
"light_5_00022.png":
{
	"frame": {"x":537,"y":1,"w":262,"h":349},
	"rotated": true,
	"trimmed": true,
	"spriteSourceSize": {"x":48,"y":0,"w":262,"h":349},
	"sourceSize": {"w":314,"h":391}
},
"light_5_00023.png":
{
	"frame": {"x":1,"y":1048,"w":262,"h":349},
	"rotated": false,
	"trimmed": true,
	"spriteSourceSize": {"x":48,"y":0,"w":262,"h":349},
	"sourceSize": {"w":314,"h":391}
},
"light_5_00024.png":
{
	"frame": {"x":265,"y":1048,"w":263,"h":348},
	"rotated": false,
	"trimmed": true,
	"spriteSourceSize": {"x":47,"y":0,"w":263,"h":348},
	"sourceSize": {"w":314,"h":391}
},
"light_5_00025.png":
{
	"frame": {"x":268,"y":699,"w":264,"h":347},
	"rotated": false,
	"trimmed": true,
	"spriteSourceSize": {"x":46,"y":0,"w":264,"h":347},
	"sourceSize": {"w":314,"h":391}
},
"light_5_00026.png":
{
	"frame": {"x":1,"y":699,"w":265,"h":347},
	"rotated": false,
	"trimmed": true,
	"spriteSourceSize": {"x":45,"y":0,"w":265,"h":347},
	"sourceSize": {"w":314,"h":391}
},
"light_5_00027.png":
{
	"frame": {"x":269,"y":350,"w":265,"h":347},
	"rotated": false,
	"trimmed": true,
	"spriteSourceSize": {"x":45,"y":0,"w":265,"h":347},
	"sourceSize": {"w":314,"h":391}
},
"light_5_00028.png":
{
	"frame": {"x":1,"y":1,"w":266,"h":347},
	"rotated": false,
	"trimmed": true,
	"spriteSourceSize": {"x":44,"y":0,"w":266,"h":347},
	"sourceSize": {"w":314,"h":391}
},
"light_5_00029.png":
{
	"frame": {"x":1,"y":350,"w":266,"h":347},
	"rotated": false,
	"trimmed": true,
	"spriteSourceSize": {"x":44,"y":0,"w":266,"h":347},
	"sourceSize": {"w":314,"h":391}
},
"light_5_00030.png":
{
	"frame": {"x":269,"y":1,"w":266,"h":347},
	"rotated": false,
	"trimmed": true,
	"spriteSourceSize": {"x":44,"y":0,"w":266,"h":347},
	"sourceSize": {"w":314,"h":391}
},
"light_5_00031.png":
{
	"frame": {"x":1,"y":350,"w":266,"h":347},
	"rotated": false,
	"trimmed": true,
	"spriteSourceSize": {"x":44,"y":0,"w":266,"h":347},
	"sourceSize": {"w":314,"h":391}
},
"light_5_00032.png":
{
	"frame": {"x":1,"y":1,"w":266,"h":347},
	"rotated": false,
	"trimmed": true,
	"spriteSourceSize": {"x":44,"y":0,"w":266,"h":347},
	"sourceSize": {"w":314,"h":391}
},
"light_5_00033.png":
{
	"frame": {"x":269,"y":350,"w":265,"h":347},
	"rotated": false,
	"trimmed": true,
	"spriteSourceSize": {"x":45,"y":0,"w":265,"h":347},
	"sourceSize": {"w":314,"h":391}
},
"light_5_00034.png":
{
	"frame": {"x":1,"y":699,"w":265,"h":347},
	"rotated": false,
	"trimmed": true,
	"spriteSourceSize": {"x":45,"y":0,"w":265,"h":347},
	"sourceSize": {"w":314,"h":391}
},
"light_5_00035.png":
{
	"frame": {"x":268,"y":699,"w":264,"h":347},
	"rotated": false,
	"trimmed": true,
	"spriteSourceSize": {"x":46,"y":0,"w":264,"h":347},
	"sourceSize": {"w":314,"h":391}
},
"light_5_00036.png":
{
	"frame": {"x":265,"y":1048,"w":263,"h":348},
	"rotated": false,
	"trimmed": true,
	"spriteSourceSize": {"x":47,"y":0,"w":263,"h":348},
	"sourceSize": {"w":314,"h":391}
},
"light_5_00037.png":
{
	"frame": {"x":1,"y":1048,"w":262,"h":349},
	"rotated": false,
	"trimmed": true,
	"spriteSourceSize": {"x":48,"y":0,"w":262,"h":349},
	"sourceSize": {"w":314,"h":391}
},
"light_5_00038.png":
{
	"frame": {"x":537,"y":1,"w":262,"h":349},
	"rotated": true,
	"trimmed": true,
	"spriteSourceSize": {"x":48,"y":0,"w":262,"h":349},
	"sourceSize": {"w":314,"h":391}
},
"light_5_00039.png":
{
	"frame": {"x":888,"y":1,"w":261,"h":349},
	"rotated": true,
	"trimmed": true,
	"spriteSourceSize": {"x":49,"y":0,"w":261,"h":349},
	"sourceSize": {"w":314,"h":391}
},
"light_5_00040.png":
{
	"frame": {"x":895,"y":1012,"w":259,"h":350},
	"rotated": false,
	"trimmed": true,
	"spriteSourceSize": {"x":51,"y":0,"w":259,"h":350},
	"sourceSize": {"w":314,"h":391}
},
"light_5_00041.png":
{
	"frame": {"x":534,"y":755,"w":258,"h":351},
	"rotated": true,
	"trimmed": true,
	"spriteSourceSize": {"x":52,"y":0,"w":258,"h":351},
	"sourceSize": {"w":314,"h":391}
},
"light_5_00042.png":
{
	"frame": {"x":1239,"y":1,"w":257,"h":352},
	"rotated": true,
	"trimmed": true,
	"spriteSourceSize": {"x":53,"y":0,"w":257,"h":352},
	"sourceSize": {"w":314,"h":391}
},
"light_5_00043.png":
{
	"frame": {"x":1156,"y":1013,"w":256,"h":352},
	"rotated": true,
	"trimmed": true,
	"spriteSourceSize": {"x":54,"y":0,"w":256,"h":352},
	"sourceSize": {"w":314,"h":391}
},
"light_5_00044.png":
{
	"frame": {"x":887,"y":755,"w":255,"h":353},
	"rotated": true,
	"trimmed": true,
	"spriteSourceSize": {"x":55,"y":0,"w":255,"h":353},
	"sourceSize": {"w":314,"h":391}
},
"light_5_00045.png":
{
	"frame": {"x":1619,"y":257,"w":254,"h":354},
	"rotated": true,
	"trimmed": true,
	"spriteSourceSize": {"x":56,"y":0,"w":254,"h":354},
	"sourceSize": {"w":314,"h":391}
},
"light_5_00046.png":
{
	"frame": {"x":1593,"y":1,"w":254,"h":354},
	"rotated": true,
	"trimmed": true,
	"spriteSourceSize": {"x":57,"y":0,"w":254,"h":354},
	"sourceSize": {"w":314,"h":391}
},
"light_5_00047.png":
{
	"frame": {"x":1510,"y":1013,"w":253,"h":354},
	"rotated": true,
	"trimmed": true,
	"spriteSourceSize": {"x":58,"y":0,"w":253,"h":354},
	"sourceSize": {"w":314,"h":391}
},
"light_5_00048.png":
{
	"frame": {"x":1618,"y":513,"w":251,"h":355},
	"rotated": true,
	"trimmed": true,
	"spriteSourceSize": {"x":60,"y":0,"w":251,"h":355},
	"sourceSize": {"w":314,"h":391}
},
"light_5_00049.png":
{
	"frame": {"x":1242,"y":761,"w":250,"h":356},
	"rotated": true,
	"trimmed": true,
	"spriteSourceSize": {"x":61,"y":0,"w":250,"h":356},
	"sourceSize": {"w":314,"h":391}
},
"light_5_00050.png":
{
	"frame": {"x":1260,"y":510,"w":249,"h":356},
	"rotated": true,
	"trimmed": true,
	"spriteSourceSize": {"x":62,"y":0,"w":249,"h":356},
	"sourceSize": {"w":314,"h":391}
},
"light_5_00051.png":
{
	"frame": {"x":1260,"y":260,"w":248,"h":357},
	"rotated": true,
	"trimmed": true,
	"spriteSourceSize": {"x":63,"y":0,"w":248,"h":357},
	"sourceSize": {"w":314,"h":391}
},
"light_5_00052.png":
{
	"frame": {"x":530,"y":1261,"w":246,"h":358},
	"rotated": true,
	"trimmed": true,
	"spriteSourceSize": {"x":65,"y":0,"w":246,"h":358},
	"sourceSize": {"w":314,"h":391}
},
"light_5_00053.png":
{
	"frame": {"x":1517,"y":1268,"w":246,"h":358},
	"rotated": true,
	"trimmed": true,
	"spriteSourceSize": {"x":65,"y":0,"w":246,"h":358},
	"sourceSize": {"w":314,"h":391}
},
"light_5_00054.png":
{
	"frame": {"x":1600,"y":766,"w":245,"h":359},
	"rotated": true,
	"trimmed": true,
	"spriteSourceSize": {"x":66,"y":0,"w":245,"h":359},
	"sourceSize": {"w":314,"h":391}
},
"light_5_00055.png":
{
	"frame": {"x":1156,"y":1271,"w":244,"h":359},
	"rotated": true,
	"trimmed": true,
	"spriteSourceSize": {"x":67,"y":0,"w":244,"h":359},
	"sourceSize": {"w":314,"h":391}
},
"light_5_00056.png":
{
	"frame": {"x":534,"y":1015,"w":244,"h":359},
	"rotated": true,
	"trimmed": true,
	"spriteSourceSize": {"x":67,"y":0,"w":244,"h":359},
	"sourceSize": {"w":314,"h":391}
},
"light_5_00057.png":
{
	"frame": {"x":899,"y":264,"w":244,"h":359},
	"rotated": true,
	"trimmed": true,
	"spriteSourceSize": {"x":67,"y":0,"w":244,"h":359},
	"sourceSize": {"w":314,"h":391}
},
"light_5_00058.png":
{
	"frame": {"x":898,"y":510,"w":243,"h":360},
	"rotated": true,
	"trimmed": true,
	"spriteSourceSize": {"x":68,"y":0,"w":243,"h":360},
	"sourceSize": {"w":314,"h":391}
},
"light_5_00059.png":
{
	"frame": {"x":536,"y":510,"w":243,"h":360},
	"rotated": true,
	"trimmed": true,
	"spriteSourceSize": {"x":68,"y":0,"w":243,"h":360},
	"sourceSize": {"w":314,"h":391}
}},
"animations": {
	"light_5": ["light_5_00000.png","light_5_00001.png","light_5_00002.png","light_5_00003.png","light_5_00004.png","light_5_00005.png","light_5_00006.png","light_5_00007.png","light_5_00008.png","light_5_00009.png","light_5_00010.png","light_5_00011.png","light_5_00012.png","light_5_00013.png","light_5_00014.png","light_5_00015.png","light_5_00016.png","light_5_00017.png","light_5_00018.png","light_5_00019.png","light_5_00020.png","light_5_00021.png","light_5_00022.png","light_5_00023.png","light_5_00024.png","light_5_00025.png","light_5_00026.png","light_5_00027.png","light_5_00028.png","light_5_00029.png","light_5_00030.png","light_5_00031.png","light_5_00032.png","light_5_00033.png","light_5_00034.png","light_5_00035.png","light_5_00036.png","light_5_00037.png","light_5_00038.png","light_5_00039.png","light_5_00040.png","light_5_00041.png","light_5_00042.png","light_5_00043.png","light_5_00044.png","light_5_00045.png","light_5_00046.png","light_5_00047.png","light_5_00048.png","light_5_00049.png","light_5_00050.png","light_5_00051.png","light_5_00052.png","light_5_00053.png","light_5_00054.png","light_5_00055.png","light_5_00056.png","light_5_00057.png","light_5_00058.png","light_5_00059.png"]
},
"meta": {
	"app": "https://www.codeandweb.com/texturepacker",
	"version": "1.1",
	"image": "light5.png",
	"format": "RGBA8888",
	"size": {"w":1974,"h":1516},
	"scale": "0.7",
	"smartupdate": "$TexturePacker:SmartUpdate:8f038bd4c4f2b5153bef69d39c17882c:5a800a2730620d44739de4da686c0483:8c9158372795e404646c09b6424f1d8b$"
}
}
